[
 {
  "context": null,
  "contributed": 0,
  "contribution_docname": null,
  "contribution_status": "",
  "docstatus": 0,
  "doctype": "Translation",
  "language": "de",
  "modified": "2024-09-02 13:13:43.949667",
  "name": "gaofstpch2",
  "source_text": "Draft",
  "translated_text": "Entwurf"
 },
 {
  "context": null,
  "contributed": 0,
  "contribution_docname": null,
  "contribution_status": "",
  "docstatus": 0,
  "doctype": "Translation",
  "language": "de",
  "modified": "2024-09-02 13:15:42.310238",
  "name": "gb1co6jil4",
  "source_text": "To be released by ADM",
  "translated_text": "Freizugeben von ADM"
 },
 {
  "context": null,
  "contributed": 0,
  "contribution_docname": null,
  "contribution_status": "",
  "docstatus": 0,
  "doctype": "Translation",
  "language": "de",
  "modified": "2024-09-02 13:20:00.159870",
  "name": "gb8n8pofv1",
  "source_text": "To be released by APP",
  "translated_text": "Freizugeben von APP"
 },
 {
  "context": null,
  "contributed": 0,
  "contribution_docname": null,
  "contribution_status": "",
  "docstatus": 0,
  "doctype": "Translation",
  "language": "de",
  "modified": "2024-09-02 13:15:15.958348",
  "name": "gbhpvjqck1",
  "source_text": "Cancellation by ADM",
  "translated_text": "Absage ADM"
 },
 {
  "context": null,
  "contributed": 0,
  "contribution_docname": null,
  "contribution_status": "",
  "docstatus": 0,
  "doctype": "Translation",
  "language": "de",
  "modified": "2024-09-02 13:16:37.073764",
  "name": "gceik5povl",
  "source_text": "Can be converted to customer",
  "translated_text": "Kann zu Kunde umgewandelt werden"
 },
 {
  "context": null,
  "contributed": 0,
  "contribution_docname": null,
  "contribution_status": "",
  "docstatus": 0,
  "doctype": "Translation",
  "language": "de",
  "modified": "2024-09-02 13:17:05.144145",
  "name": "gcnbiriisu",
  "source_text": "Marketing mailing list",
  "translated_text": "Marketingverteiler"
 },
 {
  "context": null,
  "contributed": 0,
  "contribution_docname": null,
  "contribution_status": "",
  "docstatus": 0,
  "doctype": "Translation",
  "language": "de",
  "modified": "2024-09-02 13:22:42.895994",
  "name": "gg0s7pu06s",
  "source_text": "Forward to ADM",
  "translated_text": "An ADM weitergeben"
 },
 {
  "context": null,
  "contributed": 0,
  "contribution_docname": null,
  "contribution_status": "",
  "docstatus": 0,
  "doctype": "Translation",
  "language": "de",
  "modified": "2024-09-02 13:23:54.737632",
  "name": "ggnbofjoaq",
  "source_text": "No",
  "translated_text": "Nein"
 },
 {
  "context": null,
  "contributed": 0,
  "contribution_docname": null,
  "contribution_status": "",
  "docstatus": 0,
  "doctype": "Translation",
  "language": "de",
  "modified": "2024-09-02 13:24:04.412801",
  "name": "ggqc7oh1gj",
  "source_text": "Yes",
  "translated_text": "Ja"
 },
 {
  "context": null,
  "contributed": 0,
  "contribution_docname": null,
  "contribution_status": "",
  "docstatus": 0,
  "doctype": "Translation",
  "language": "de",
  "modified": "2024-09-02 13:27:40.353675",
  "name": "gitrkf1beu",
  "source_text": "Reopen",
  "translated_text": "Wieder öffnen"
 },
 {
  "context": null,
  "contributed": 0,
  "contribution_docname": null,
  "contribution_status": "",
  "docstatus": 0,
  "doctype": "Translation",
  "language": "de",
  "modified": "2024-09-02 13:29:16.788226",
  "name": "gjl90a7e63",
  "source_text": "Forward marketing mailing list",
  "translated_text": "weitergeben Marketingverteiler"
 }
]